cellacdc/QtScoped.py
cellacdc/SingleCellSeg.py
cellacdc/__init__.py
cellacdc/__main__.py
cellacdc/_base_widgets.py
cellacdc/_core.py
cellacdc/_debug.py
cellacdc/_get_app_palette.py
cellacdc/_main.py
cellacdc/_palettes.py
cellacdc/_process.py
cellacdc/_run.py
cellacdc/_types.py
cellacdc/_version.py
cellacdc/_view_all_buttons.py
cellacdc/_view_all_icons.py
cellacdc/_warnings.py
cellacdc/acdc_regex.py
cellacdc/annotate.py
cellacdc/apps.py
cellacdc/autopilot.py
cellacdc/cca_functions.py
cellacdc/cli.py
cellacdc/code_structure.md
cellacdc/colors.py
cellacdc/config.py
cellacdc/core.py
cellacdc/data.py
cellacdc/dataPrep.py
cellacdc/dataReStruct.py
cellacdc/dataStruct.py
cellacdc/debugutils.py
cellacdc/exporters.py
cellacdc/features.py
cellacdc/gui.py
cellacdc/gui_utils.py
cellacdc/html_utils.py
cellacdc/info.py
cellacdc/io.py
cellacdc/load.py
cellacdc/measure.py
cellacdc/measurements.py
cellacdc/myutils.py
cellacdc/path.py
cellacdc/plot.py
cellacdc/preprocess.py
cellacdc/prompts.py
cellacdc/qrc_resources_dark.py
cellacdc/qrc_resources_light.py
cellacdc/qutils.py
cellacdc/record.py
cellacdc/resources_dark.qrc
cellacdc/resources_light.qrc
cellacdc/segm.py
cellacdc/segmentation.py
cellacdc/syntax.py
cellacdc/test_segm_model.py
cellacdc/test_tracker.py
cellacdc/transformation.py
cellacdc/urls.py
cellacdc/whitelist.py
cellacdc/widgets.py
cellacdc/workers.py
cellacdc/_deprecated/filters.py
cellacdc/_html/__init__.py
cellacdc/_html/gui_welcome.html
cellacdc/_profile/spline_to_obj/1_exec_time_space_size_step_10.csv
cellacdc/_profile/spline_to_obj/__init__.py
cellacdc/_profile/spline_to_obj/model.py
cellacdc/_profile/spline_to_obj/profile_skimage_draw_polygon.py
cellacdc/acdc_bioio_bioformats/__init__.py
cellacdc/acdc_bioio_bioformats/_init_reader.py
cellacdc/acdc_bioio_bioformats/_read_metadata.py
cellacdc/acdc_bioio_bioformats/_read_sample_data.py
cellacdc/acdc_bioio_bioformats/_save_data.py
cellacdc/acdc_bioio_bioformats/_save_data_single_channel.py
cellacdc-1.6.12.dist-info/licenses/LICENSE
cellacdc-1.6.12.dist-info/METADATA
cellacdc-1.6.12.dist-info/WHEEL
cellacdc-1.6.12.dist-info/entry_points.txt
cellacdc-1.6.12.dist-info/top_level.txt
cellacdc-1.6.12.dist-info/RECORD
