Metadata-Version: 2.4
Name: cellacdc
Version: 1.6.12
Summary: Cell segmentation, tracking and event annotation
Author-email: Francesco Padovani and Benedikt Mairhoermann <francesco.padovani@helmholtz-muenchen.de>
License-Expression: BSD-3-Clause
Project-URL: GitHub page, https://github.com/SchmollerLab/Cell_ACDC
Project-URL: Author contact, https://schmollerlab.com/francescopadovani
Project-URL: Schmoller lab, https://schmollerlab.com/
Keywords: live-cell imaging,cell segmentation,cell tracking,cell cycle annotations,image analysis
Classifier: Development Status :: 4 - Beta
Classifier: Programming Language :: Python :: 3 :: Only
Classifier: Programming Language :: Python :: 3.10
Classifier: Programming Language :: Python :: 3.11
Classifier: Programming Language :: Python :: 3.12
Classifier: Intended Audience :: Education
Classifier: Intended Audience :: Science/Research
Classifier: Operating System :: Microsoft :: Windows
Classifier: Operating System :: POSIX
Classifier: Operating System :: Unix
Classifier: Operating System :: MacOS
Classifier: Topic :: Scientific/Engineering
Classifier: Topic :: Scientific/Engineering :: Bio-Informatics
Classifier: Topic :: Scientific/Engineering :: Information Analysis
Classifier: Topic :: Scientific/Engineering :: Image Processing
Classifier: Topic :: Scientific/Engineering :: Visualization
Classifier: Topic :: Utilities
Requires-Python: >=3.10
License-File: LICENSE
Requires-Dist: numpy
Requires-Dist: pandas
Requires-Dist: opencv-python-headless
Requires-Dist: natsort
Requires-Dist: h5py
Requires-Dist: scikit-image>=0.18
Requires-Dist: tqdm
Requires-Dist: scikit-learn
Requires-Dist: psutil
Requires-Dist: boto3
Requires-Dist: requests
Requires-Dist: setuptools-scm
Provides-Extra: gui
Requires-Dist: qtpy; extra == "gui"
Requires-Dist: pyqtgraph>=0.13.7; extra == "gui"
Requires-Dist: seaborn; extra == "gui"
Requires-Dist: PyQt6; extra == "gui"
Provides-Extra: pyqt6
Requires-Dist: PyQt6; extra == "pyqt6"
Provides-Extra: pyqt5
Requires-Dist: PyQt5; extra == "pyqt5"
Provides-Extra: pyside2
Requires-Dist: PySide2; extra == "pyside2"
Provides-Extra: pyside6
Requires-Dist: PySide6; extra == "pyside6"
Provides-Extra: torch
Requires-Dist: torchvision; extra == "torch"
Provides-Extra: tf
Requires-Dist: tensorflow<2.16; extra == "tf"
Provides-Extra: tensorflow
Requires-Dist: tensorflow<2.16; extra == "tensorflow"
Provides-Extra: pytorch
Requires-Dist: torchvision; extra == "pytorch"
Provides-Extra: cellpose3
Requires-Dist: cellpose<4.0.0; extra == "cellpose3"
Provides-Extra: stardist
Requires-Dist: tensorflow<2.17; extra == "stardist"
Requires-Dist: numpy<2.0.0; extra == "stardist"
Requires-Dist: stardist; extra == "stardist"
Provides-Extra: yeaz
Requires-Dist: yeaz; extra == "yeaz"
Provides-Extra: trackastra
Requires-Dist: trackastra; extra == "trackastra"
Provides-Extra: deepsea
Requires-Dist: torch; extra == "deepsea"
Requires-Dist: deepsea; extra == "deepsea"
Requires-Dist: munkres; extra == "deepsea"
Provides-Extra: all
Requires-Dist: PyQt6; extra == "all"
Requires-Dist: torchvision; extra == "all"
Requires-Dist: tensorflow<2.16; extra == "all"
Requires-Dist: tables; extra == "all"
Dynamic: license-file
